iam/__init__.py
iam/abstracts.py
iam/apps.py
iam/factories.py
iam/mixins.py
iam/predicates.py
iam/registry.py
iam/utils.py
iam/contrib/__init__.py
iam/contrib/perms.py
iam/contrib/predicates.py
iam/contrib/utils.py
iam/contrib/admin/__init__.py
iam/contrib/admin/admin.py
iam/contrib/admin/mixins.py
iam/contrib/users/__init__.py
iam/contrib/users/admin.py
iam/contrib/users/models.py
iam/rest/__init__.py
iam/rest/fields.py
iam/rest/serializers.py
tests/__init__.py
tests/test_factories.py
tests/test_perms.py
tests/test_roles.py
django_iam-0.3.0.dist-info/LICENSE
django_iam-0.3.0.dist-info/METADATA
django_iam-0.3.0.dist-info/WHEEL
django_iam-0.3.0.dist-info/top_level.txt
django_iam-0.3.0.dist-info/RECORD
